unhandled_exception_logger.py
unhandled_exception_logger-0.0.3.dist-info/METADATA
unhandled_exception_logger-0.0.3.dist-info/WHEEL
unhandled_exception_logger-0.0.3.dist-info/top_level.txt
unhandled_exception_logger-0.0.3.dist-info/RECORD
