Metadata-Version: 2.1
Name: unhandled-exception-logger
Version: 0.0.3
Summary: Log unhandled exceptions as critical
Home-page: https://github.com/karmacomputing/unhandled_exception
Author: Chris Simpson
Author-email: oss@karmacomputing.co.uk
License: UNKNOWN
Platform: UNKNOWN
Classifier: License :: OSI Approved :: GNU General Public License v3 (GPLv3)
